{
  "enable_development_mode": false,
  "company_name": "Johnson Orthodontics",
  "domain": "huntsvilleortho.com",
  "email": "info@huntsvilleortho.com",
  "phone": {
    "number": "",
    "href": "",
    "aria": ""
  },
  "location": [
    {
      "title": "Huntsville Office",
      "address": {
        "street": "",
        "suite": "",
        "city_state": "Huntsville, AL",
        "coordinates": {
          "longitude": "",
          "latitude": ""
        }
      },
      "phone": {
        "number": "",
        "href": ""
      },
      "email": "info@huntsvilleortho.com",
      "hours": [
        {
          "day": "Mon",
          "time": "8:30 - 5:00"
        },
        {
          "day": "Tues - Thurs",
          "time": "8:30 - 5:00"
        },
        {
          "day": "Fri",
          "time": "8:30 - 1:00"
        },
        {
          "day": "Sat - Sun",
          "time": "Closed"
        }
      ],
      "directions_link": {
        "href": "",
        "label": "Get Directions"
      },
      "special_note": ""
    }
  ],
  "typography": [
    {
      "label": "font",
      "font": "'Open Sans', helvetica, arial, sans-serif"
    },
    {
      "label": "font-title",
      "font": "'Archivo', sans-serif"
    }
  ],
  "top_bar": {
    "enable_top_bar": true,
    "type": "links",
    "theme": "light",
    "content_alignment": "right",
    "links": [
      {
        "icon": "phone",
        "text": "Free Consults — Book Online",
        "href": "https://huntsvilleortho.com/free-consult",
        "label": "Book a free consultation",
        "new_window": true
      },
      {
        "icon": "envelope",
        "text": "info@huntsvilleortho.com",
        "href": "mailto:info@huntsvilleortho.com",
        "label": "Email Johnson Orthodontics",
        "new_window": false
      }
    ],
    "announcement": {
      "icon": "tooth-two-v1",
      "label": "Free Consultation",
      "text": "Free consultations and same-day starts available. Click to learn more.",
      "mobile_text": "Free Consultation",
      "modal": {
        "title": "Free Consultation",
        "text": "<p>At Johnson Orthodontics we offer a complimentary consultation to discuss goals, digital scans, and same-day starts when appropriate. Book online or call our office to reserve your appointment.</p>"
      }
    }
  },
  "nav": {
    "cta_buttons": true,
    "buttons": [
      {
        "button": {
          "type": "nuxt",
          "style": "primary",
          "label": "Free Consult",
          "aria_label": "Schedule a free consultation",
          "href": "https://huntsvilleortho.com/free-consult",
          "path": "",
          "hash": "",
          "external": true,
          "include_icon": false,
          "icon": "pencil",
          "color": "primary"
        }
      },
      {
        "button": {
          "type": "nuxt",
          "style": "secondary",
          "label": "New Patients",
          "aria_label": "New patients and forms",
          "href": "https://huntsvilleortho.com/new-patients",
          "path": "",
          "hash": "",
          "external": true,
          "include_icon": false,
          "icon": "envelope",
          "color": "accent"
        }
      },
      {
        "button": {
          "type": "nuxt",
          "style": "underline",
          "label": "Our Treatments",
          "aria_label": "Learn about treatments",
          "href": "https://huntsvilleortho.com/our-treatments/",
          "path": "",
          "hash": "",
          "external": true,
          "include_icon": false,
          "icon": "tooth-check",
          "color": "black"
        }
      }
    ],
    "floating": true
  },
  "footer": {
    "social_media": [
      {
        "href": "/#",
        "icon": "facebook"
      },
      {
        "href": "/#",
        "icon": "instagram"
      },
      {
        "href": "/#",
        "icon": "yelp"
      },
      {
        "href": "/#",
        "icon": "google"
      }
    ],
    "add_border": false
  },
  "enable_popup": false,
  "popup": {
    "title": "Welcome to Johnson Orthodontics",
    "text": "",
    "image": {
      "src": "",
      "webp": "",
      "alt": "",
      "aria_hidden": false,
      "bgColor": "",
      "imageBackground": false,
      "addLoader": false,
      "objectPosition": "",
      "forceAlt": "",
      "loading_mask": "",
      "image_selection_hints": {
        "context_category": "New Patients Hero"
      }
    }
  }
}